icechart/__init__.py
icechart/common.py
icechart/icechart.py
icechart/utils.py
icechart-0.0.6.dist-info/LICENSE
icechart-0.0.6.dist-info/METADATA
icechart-0.0.6.dist-info/WHEEL
icechart-0.0.6.dist-info/dependency_links.txt
icechart-0.0.6.dist-info/top_level.txt
icechart-0.0.6.dist-info/RECORD
