Metadata-Version: 2.1
Name: icechart
Version: 0.0.6
Summary: A python package for icesat data analysis
Home-page: https://github.com/Surfix/icechart
Author: Naheem Adebisi
Author-email: adebisi.naheem@gmail.com
License: MIT license
Keywords: icechart
Platform: UNKNOWN
Classifier: Development Status :: 2 - Pre-Alpha
Classifier: Intended Audience :: Developers
Classifier: License :: OSI Approved :: MIT License
Classifier: Natural Language :: English
Classifier: Programming Language :: Python :: 3
Classifier: Programming Language :: Python :: 3.5
Classifier: Programming Language :: Python :: 3.6
Classifier: Programming Language :: Python :: 3.7
Classifier: Programming Language :: Python :: 3.8
Requires-Python: >=3.5
Requires-Dist: earthengine-api
Requires-Dist: folium
Requires-Dist: ipyleaflet
Requires-Dist: pyshp
